picture_text/__init__.py
picture_text/picture_text.py
picture_text/src/__init__.py
picture_text/src/hac_tools.py
picture_text/src/treemap.py
picture_text/src/utils.py
picture_text-0.1.0.dist-info/LICENSE
picture_text-0.1.0.dist-info/METADATA
picture_text-0.1.0.dist-info/WHEEL
picture_text-0.1.0.dist-info/top_level.txt
picture_text-0.1.0.dist-info/RECORD
