Metadata-Version: 2.1
Name: picture-text
Version: 0.1.0
Summary: Interactive tree-maps for text corpora with SBERT & Hierarchical Clustering (HAC)
Home-page: https://github.com/md-experiments/picture_text
Author: Mihail Dungarov
Author-email: deeplearnmd@gmail.com
License: Apache License 2.0
Keywords: hierarchical agglomerative clustering,hac,treemap,interactive visualization,data visualization,deep learning,machine learning,transformers,sentence-transformers,BERT,SBERT,nlp,natural language processing,text,ai,ml
Platform: UNKNOWN
Classifier: Development Status :: 5 - Production/Stable
Classifier: Intended Audience :: Developers
Classifier: Intended Audience :: Education
Classifier: Intended Audience :: Science/Research
Classifier: License :: OSI Approved :: Apache Software License
Classifier: Operating System :: OS Independent
Classifier: Programming Language :: Python :: 3
Classifier: Programming Language :: Python :: 3.6
Classifier: Programming Language :: Python :: 3.7
Classifier: Topic :: Scientific/Engineering :: Artificial Intelligence
Requires-Dist: numpy (>=1.14.0)
Requires-Dist: pandas (>=0.20.0)
Requires-Dist: fastcluster (>=1.1.26)
Requires-Dist: sentence-transformers (>=0.3.4)
Requires-Dist: transformers (>=3.0.2)
Requires-Dist: scipy (>=1.1.0)
Requires-Dist: matplotlib (>=3.0.0)
Requires-Dist: plotly (>=4.10.0)
